{
  "$schema" : "https:\/\/schema.linearmouse.app\/0.10.0",
  "schemes" : [
    {
      "if" : {
        "device" : {
          "vendorID" : "0x46d",
          "productID" : "0xc53f",
          "productName" : "USB Receiver",
          "category" : "mouse"
        }
      },
      "scrolling" : {
        "distance" : {
          "vertical" : "auto"
        },
        "reverse" : {
          "vertical" : true
        },
        "speed" : {
          "vertical" : 0
        },
        "acceleration" : {
          "vertical" : 1
        }
      }
    }
  ]
}